graph_reader/__init__.py
graph_reader/config.py
graph_reader/reader.py
graph_reader/schema.py
graph_reader/indexers/__init__.py
graph_reader/indexers/base_indexer.py
graph_reader/indexers/memory_indexer.py
graph_reader/indexers/search_expression.py
graph_reader/indexers/sqlite_indexer.py
beanone_graph-0.3.0.dist-info/METADATA
beanone_graph-0.3.0.dist-info/WHEEL
beanone_graph-0.3.0.dist-info/licenses/LICENSE
beanone_graph-0.3.0.dist-info/RECORD
