Metadata-Version: 2.4
Name: beanone-graph
Version: 0.3.0
Summary: Graph generation and storage library with update tracking
Project-URL: Homepage, https://github.com/beanone/graph_reader
Project-URL: Repository, https://github.com/beanone/graph_reader
Author-email: Beanone Team <beanone@example.com>
License-Expression: MIT
License-File: LICENSE
Classifier: Development Status :: 3 - Alpha
Classifier: Intended Audience :: Developers
Classifier: License :: OSI Approved :: MIT License
Classifier: Programming Language :: Python :: 3.12
Classifier: Topic :: Scientific/Engineering :: Artificial Intelligence
Classifier: Topic :: Software Development :: Libraries :: Python Modules
Requires-Python: >=3.7
